flaskFormRequest/__init__.py
flaskFormRequest/formRequest.py
flaskFormRequest/decorators/__init__.py
flaskFormRequest/filters/__init__.py
flaskFormRequest/validators/__init__.py
flaskFormRequest/validators/accepted.py
flaskFormRequest/validators/after.py
flaskFormRequest/validators/afterOrEqual.py
flaskFormRequest/validators/alpha.py
flaskFormRequest/validators/alphaDash.py
flaskFormRequest/validators/alphaNum.py
flaskFormRequest/validators/array.py
flaskFormRequest/validators/before.py
flaskFormRequest/validators/beforeOrEqual.py
flaskFormRequest/validators/between.py
flaskFormRequest/validators/boolean.py
flaskFormRequest/validators/callable.py
flaskFormRequest/validators/confirmed.py
flaskFormRequest/validators/currentPassword.py
flaskFormRequest/validators/date.py
flaskFormRequest/validators/dateEquals.py
flaskFormRequest/validators/declined.py
flaskFormRequest/validators/different.py
flaskFormRequest/validators/digits.py
flaskFormRequest/validators/digitsBetween.py
flaskFormRequest/validators/distinct.py
flaskFormRequest/validators/email.py
flaskFormRequest/validators/exists.py
flaskFormRequest/validators/file.py
flaskFormRequest/validators/filled.py
flaskFormRequest/validators/float.py
flaskFormRequest/validators/gt.py
flaskFormRequest/validators/gte.py
flaskFormRequest/validators/inRule.py
flaskFormRequest/validators/integer.py
flaskFormRequest/validators/ip.py
flaskFormRequest/validators/jsonRule.py
flaskFormRequest/validators/lt.py
flaskFormRequest/validators/lte.py
flaskFormRequest/validators/macAddress.py
flaskFormRequest/validators/max.py
flaskFormRequest/validators/mimeTypes.py
flaskFormRequest/validators/min.py
flaskFormRequest/validators/notIn.py
flaskFormRequest/validators/notInRule.py
flaskFormRequest/validators/notRegex.py
flaskFormRequest/validators/nullable.py
flaskFormRequest/validators/numeric.py
flaskFormRequest/validators/prohibited.py
flaskFormRequest/validators/regex.py
flaskFormRequest/validators/required.py
flask_FormRequest-0.0.32.dist-info/LICENSE
flask_FormRequest-0.0.32.dist-info/METADATA
flask_FormRequest-0.0.32.dist-info/WHEEL
flask_FormRequest-0.0.32.dist-info/top_level.txt
flask_FormRequest-0.0.32.dist-info/RECORD
