Metadata-Version: 2.1
Name: flask-FormRequest
Version: 0.0.32
Summary: Request validator for flask
Author: edcilo
Classifier: Programming Language :: Python :: 3
Classifier: License :: OSI Approved :: MIT License
Classifier: Operating System :: OS Independent
Requires-Python: >=3.8
License-File: LICENSE
Requires-Dist: email-validator (==1.1.3)
